langsa_system/__init__.py
langsa_system/gg.py
langsa_system/langsa.py
langsa_system/浪飒.py
langsa_system-2.1.dist-info/LICENSE
langsa_system-2.1.dist-info/METADATA
langsa_system-2.1.dist-info/WHEEL
langsa_system-2.1.dist-info/top_level.txt
langsa_system-2.1.dist-info/RECORD
