Metadata-Version: 2.1
Name: langsa-system
Version: 2.1
Summary: langsa-system：浪飒（langsa）进制，代表自己的进制
Home-page: https://github.com/langsasec/langsa-system
Author: 浪飒
Author-email: langsa-hy@qq.com
License: GPL
License-File: LICENSE
